django_person_client-1.1.2.dist-info/licenses/LICENSE
uw_person_client/VERSION
uw_person_client/__init__.py
uw_person_client/exceptions.py
uw_person_client/models.py
uw_person_client/urls.py
uw_person_client/fixtures/adviser.json
uw_person_client/fixtures/degree.json
uw_person_client/fixtures/employee.json
uw_person_client/fixtures/hold.json
uw_person_client/fixtures/major.json
uw_person_client/fixtures/person.json
uw_person_client/fixtures/sport.json
uw_person_client/fixtures/student.json
uw_person_client/fixtures/term.json
uw_person_client/fixtures/transcript.json
uw_person_client/fixtures/transfer.json
uw_person_client/test_migrations/0001_initial.py
uw_person_client/test_migrations/0002_alter_ordering_options.py
uw_person_client/test_migrations/0003_enrolledstudentqueue_personqueue_and_more.py
uw_person_client/test_migrations/__init__.py
uw_person_client/tests/__init__.py
uw_person_client/tests/test_adviser.py
uw_person_client/tests/test_major.py
uw_person_client/tests/test_person.py
uw_person_client/tests/test_person_queue.py
django_person_client-1.1.2.dist-info/METADATA
django_person_client-1.1.2.dist-info/WHEEL
django_person_client-1.1.2.dist-info/top_level.txt
django_person_client-1.1.2.dist-info/RECORD
