Metadata-Version: 2.4
Name: Django-Person-Client
Version: 1.1.2
Summary: A UW Person Client Django app
Home-page: https://github.com/uw-it-aca/django-person-client
Author: UW-IT Student & Educational Technology Services
Author-email: aca-it@uw.edu
License: Apache License, Version 2.0
Classifier: Intended Audience :: Developers
Classifier: License :: OSI Approved :: Apache Software License
Classifier: Operating System :: OS Independent
Classifier: Programming Language :: Python
License-File: LICENSE
Requires-Dist: django<6,>=4.2
Requires-Dist: psycopg2
Requires-Dist: uw-restclients-pws
Dynamic: author
Dynamic: author-email
Dynamic: classifier
Dynamic: description
Dynamic: home-page
Dynamic: license
Dynamic: license-file
Dynamic: requires-dist
Dynamic: summary
